[
    {"name": "AUD", "group": 0},
    {"name": "OMP", "group": 1},
    {"name": "HID", "group": 2},
    {"name": "DEB", "group": 3},
    {"name": "SGC", "group": 4},
    {"name": "LLR", "group": 5},
    {"name": "VFX", "group": 6},
    {"name": "FES", "group": 7},
    {"name": "PLA", "group": 8},
    {"name": "GMP", "group": 9},
    {"name": "SDK", "group": 10},
    {"name": "SKA", "group": 11},
    {"name": "PHY", "group": 12},
    {"name": "RES", "group": 13},
    {"name": "COR", "group": 14},
    {"name": "EDI", "group": 15}
]